Metadata-Version: 2.1
Name: articleDateExtract
Version: 0.10
Summary: Automatically extracts and normalizes an online article or blog post publication date
Home-page: https://github.com/blueshirtdeveloper/article-date-extract
Author: Krishna Kishore
Author-email: imwebruster@gmail.com
License: MIT
Platform: UNKNOWN
Classifier: Development Status :: 4 - Beta
Classifier: Intended Audience :: Developers
Classifier: Natural Language :: English
Classifier: License :: OSI Approved :: MIT License
Classifier: Programming Language :: Python
Classifier: Programming Language :: Python :: 3
Classifier: Programming Language :: Python :: 3.6
Classifier: Programming Language :: Python :: 3.8
